LICENSE
MANIFEST.in
README.rst
setup.py
bin/shcol
bin/shcol.bat
shcol/__init__.py
shcol/__main__.py
shcol/cli.py
shcol/config.py
shcol/highlevel.py
shcol.egg-info/PKG-INFO
shcol.egg-info/SOURCES.txt
shcol.egg-info/dependency_links.txt
shcol.egg-info/top_level.txt
shcol/core/__init__.py
shcol/core/columncalc.py
shcol/core/formatters.py
shcol/helpers/__init__.py
shcol/helpers/misc.py
shcol/helpers/termwidth.py
testsuite/test_cli.py
testsuite/test_core.py
testsuite/test_highlevel.py
testsuite/test_script.py