Metadata-Version: 1.1
Name: shcol
Version: 0.3
Summary: A shell columnizer
Home-page: https://github.com/seblin/shcol
Author: Sebastian Linke
Author-email: Seb_Linke@arcor.de
License: Simplified BSD
Platform: any
Classifier: Development Status :: 4 - Beta
Classifier: Environment :: Console
Classifier: Intended Audience :: Developers
Classifier: Intended Audience :: End Users/Desktop
Classifier: License :: OSI Approved :: BSD License
Classifier: Natural Language :: English
Classifier: Operating System :: OS Independent
Classifier: Programming Language :: Python :: 2.7
Classifier: Programming Language :: Python :: 3.2
Classifier: Programming Language :: Python :: 3.3
Classifier: Programming Language :: Python :: 3.4
Classifier: Topic :: System :: Shells
